signplus/__init__.py
signplus/sdk.py
signplus/sdk_async.py
signplus/hooks/__init__.py
signplus/hooks/hook.py
signplus/models/__init__.py
signplus/models/add_annotation_request.py
signplus/models/add_envelope_document_request.py
signplus/models/add_envelope_signing_steps_request.py
signplus/models/add_template_document_request.py
signplus/models/add_template_signing_steps_request.py
signplus/models/annotation.py
signplus/models/annotation_checkbox.py
signplus/models/annotation_checkbox_style.py
signplus/models/annotation_date_time.py
signplus/models/annotation_date_time_format.py
signplus/models/annotation_font.py
signplus/models/annotation_font_family.py
signplus/models/annotation_initials.py
signplus/models/annotation_signature.py
signplus/models/annotation_text.py
signplus/models/annotation_type.py
signplus/models/attachment_placeholder.py
signplus/models/attachment_placeholder_file.py
signplus/models/attachment_placeholder_request.py
signplus/models/attachment_placeholders_per_recipient.py
signplus/models/attachment_settings.py
signplus/models/create_envelope_from_template_request.py
signplus/models/create_envelope_request.py
signplus/models/create_template_request.py
signplus/models/create_webhook_request.py
signplus/models/document.py
signplus/models/dynamic_field.py
signplus/models/envelope.py
signplus/models/envelope_attachments.py
signplus/models/envelope_flow_type.py
signplus/models/envelope_legality_level.py
signplus/models/envelope_notification.py
signplus/models/envelope_order_field.py
signplus/models/envelope_status.py
signplus/models/list_envelope_document_annotations_response.py
signplus/models/list_envelope_documents_response.py
signplus/models/list_envelopes_request.py
signplus/models/list_envelopes_response.py
signplus/models/list_template_annotations_response.py
signplus/models/list_template_document_annotations_response.py
signplus/models/list_template_documents_response.py
signplus/models/list_templates_request.py
signplus_python-1.4.0.dist-info/licenses/LICENSE
signplus_python-1.4.0.dist-info/METADATA
signplus_python-1.4.0.dist-info/WHEEL
signplus_python-1.4.0.dist-info/top_level.txt
signplus_python-1.4.0.dist-info/RECORD
