Metadata-Version: 2.4
Name: signplus-python
Version: 1.4.0
Summary: Integrate legally-binding electronic signature to your workflow
License: MIT
Requires-Python: >=3.9
License-File: LICENSE
Requires-Dist: requests>=2.31.0
Dynamic: license-file
